{
  "l2_logreg": {
    "C": 1.0,
    "penalty": "l2",
    "solver": "lbfgs",
    "max_iter": 100
  },
  "l2_linreg": {
    "fit_intercept": true,
    "positive": false
  },
  "xgboost_clf": {
    "learning_rate": 0.3,
    "max_depth": 6,
    "n_estimators": 100,
    "subsample": 1.0,
    "colsample_bytree": 1.0,
    "gamma": 0,
    "min_child_weight": 1,
    "verbose": 0
  },
  "xgboost_reg": {
    "learning_rate": 0.3,
    "max_depth": 6,
    "n_estimators": 100,
    "subsample": 1.0,
    "colsample_bytree": 1.0,
    "gamma": 0,
    "min_child_weight": 1,
    "objective": "reg:squarederror",
    "verbose": 0
  },
  "lgbm_clf": {
    "learning_rate": 0.1,
    "n_estimators": 100,
    "num_leaves": 31,
    "max_depth": -1,
    "min_child_samples": 20,
    "subsample": 1.0,
    "colsample_bytree": 1.0,
    "verbose": -1
  },
  "lgbm_reg": {
    "learning_rate": 0.1,
    "n_estimators": 100,
    "num_leaves": 31,
    "max_depth": -1,
    "min_child_samples": 20,
    "subsample": 1.0,
    "colsample_bytree": 1.0,
    "objective": "regression",
    "verbose": -1
  },
  "catboost_clf": {
    "iterations": 1000,
    "learning_rate": 0.03,
    "depth": 6,
    "l2_leaf_reg": 3.0,
    "border_count": 254,
    "bagging_temperature": 1.0,
    "random_strength": 1.0,
    "verbose": 0
  },
  "catboost_reg": {
    "iterations": 1000,
    "learning_rate": 0.03,
    "depth": 6,
    "l2_leaf_reg": 3.0,
    "border_count": 254,
    "bagging_temperature": 1.0,
    "random_strength": 1.0,
    "loss_function": "RMSE",
    "verbose": 0
  },
  "extra_trees_clf": {
    "n_estimators": 100,
    "criterion": "gini",
    "max_depth": null,
    "min_samples_split": 2,
    "min_samples_leaf": 1,
    "max_features": "sqrt",
    "bootstrap": false
  },
  "extra_trees_reg": {
    "n_estimators": 100,
    "criterion": "squared_error",
    "max_depth": null,
    "min_samples_split": 2,
    "min_samples_leaf": 1,
    "max_features": 1.0,
    "bootstrap": false
  }
}
